LICENSE
MANIFEST.in
README.rst
docs-requirements.txt
setup.cfg
setup.py
tox.ini
docs/Makefile
docs/conf.py
docs/contrib.rst
docs/index.rst
docs/installation.rst
docs/intro.rst
docs/module.rst
docs/usage.rst
oscar.flag.egg-info/PKG-INFO
oscar.flag.egg-info/SOURCES.txt
oscar.flag.egg-info/dependency_links.txt
oscar.flag.egg-info/namespace_packages.txt
oscar.flag.egg-info/pbr.json
oscar.flag.egg-info/requires.txt
oscar.flag.egg-info/top_level.txt
oscar.flag.egg-info/zip-safe
oscar/flag/__init__.py
oscar/flag/contrib.py
test/contrib_test.py
test/flag_test.py