Metadata-Version: 1.1
Name: oscar.flag
Version: 0.1.2
Summary: Configuration flags for libraries and applications.
Home-page: https://github.com/oscarhealth/oscar.flag
Author: Oscar Engineering
Author-email: open-source+oscar.flag@hioscar.com
License: Apache Software License 2.0
Keywords: command-line arguments environment flags argv
Platform: UNKNOWN
Classifier: Development Status :: 5 - Production/Stable
Classifier: Intended Audience :: Developers
Classifier: Intended Audience :: System Administrators
Classifier: License :: OSI Approved :: Apache Software License
Classifier: Operating System :: OS Independent
Classifier: Programming Language :: Python :: 2
Classifier: Programming Language :: Python :: 2.6
Classifier: Programming Language :: Python :: 2.7
Classifier: Topic :: Software Development :: Libraries
Classifier: Topic :: System :: Systems Administration
